kernpy/__init__.py
kernpy/__main__.py
kernpy/test_grammar.sh
kernpy/visualize_analysis.sh
kernpy/core/__init__.py
kernpy/core/_io.py
kernpy/core/base_antlr_importer.py
kernpy/core/base_antlr_spine_parser_listener.py
kernpy/core/basic_spine_importer.py
kernpy/core/document.py
kernpy/core/dyn_importer.py
kernpy/core/dynam_spine_importer.py
kernpy/core/error_listener.py
kernpy/core/exporter.py
kernpy/core/fing_spine_importer.py
kernpy/core/generic.py
kernpy/core/gkern.py
kernpy/core/graphviz_exporter.py
kernpy/core/harm_spine_importer.py
kernpy/core/import_humdrum_old.py
kernpy/core/importer.py
kernpy/core/importer_factory.py
kernpy/core/kern_spine_importer.py
kernpy/core/mens_spine_importer.py
kernpy/core/mhxm_spine_importer.py
kernpy/core/pitch_models.py
kernpy/core/root_spine_importer.py
kernpy/core/spine_importer.py
kernpy/core/text_spine_importer.py
kernpy/core/tokenizers.py
kernpy/core/tokens.py
kernpy/core/transposer.py
kernpy/core/generated/kernSpineLexer.interp
kernpy/core/generated/kernSpineLexer.py
kernpy/core/generated/kernSpineLexer.tokens
kernpy/core/generated/kernSpineParser.interp
kernpy/core/generated/kernSpineParser.py
kernpy/core/generated/kernSpineParser.tokens
kernpy/core/generated/kernSpineParserListener.py
kernpy/core/generated/kernSpineParserVisitor.py
kernpy/io/__init__.py
kernpy/io/public.py
kernpy/polish_scores/__init__.py
kernpy/polish_scores/download_polish_dataset.py
kernpy/polish_scores/iiif.py
kernpy/util/__init__.py
kernpy/util/helpers.py
kernpy/util/store_cache.py
kernpy-1.3.0.dist-info/METADATA
kernpy-1.3.0.dist-info/WHEEL
kernpy-1.3.0.dist-info/RECORD
