Metadata-Version: 2.4
Name: kernpy
Version: 1.3.0
Summary: Python Humdrum **kern and **mens utilities
Project-URL: Homepage, https://github.com/OMR-PRAIG-UA-ES/kernpy
Project-URL: Documentation, https://github.com/OMR-PRAIG-UA-ES/kernpy#readme
Project-URL: Issues, https://github.com/OMR-PRAIG-UA-ES/kernpy/issues
Author-email: David Rizo Valero <drizo@ua.es>, Joan Cerveto Serrano <joan.cerveto@ua.es>
License: AGPL-3.0-only
Classifier: License :: OSI Approved :: GNU Affero General Public License v3
Classifier: Operating System :: OS Independent
Classifier: Programming Language :: Python :: 3
Requires-Python: >=3.9
Requires-Dist: antlr4-python3-runtime>=4.13.2
Requires-Dist: pillow
Requires-Dist: requests
Requires-Dist: urllib3>=1.26.6
